hatch_vcs_footgun_example/__init__.py
hatch_vcs_footgun_example/main.py
hatch_vcs_footgun_example/version.py
hatch_vcs_footgun_example-2.0.1.dist-info/METADATA
hatch_vcs_footgun_example-2.0.1.dist-info/WHEEL
hatch_vcs_footgun_example-2.0.1.dist-info/licenses/LICENSE
hatch_vcs_footgun_example-2.0.1.dist-info/RECORD
