Metadata-Version: 2.4
Name: hatch-vcs-footgun-example
Version: 2.0.1
Project-URL: Homepage, https://github.com/maresb/hatch-vcs-footgun-example
License: This is free and unencumbered software released into the public domain.
License-File: LICENSE
